{"stats":{"minecraft:crafted":{"minecraft:torch":16},"minecraft:used":{"utdmod:ritual_block":26,"minecraft:torch":8,"minecraft:cobblestone":2,"minecraft:stone_pickaxe":66},"minecraft:custom":{"minecraft:open_chest":1,"minecraft:time_since_rest":9593,"minecraft:play_time":9593,"minecraft:sprint_one_cm":6726,"minecraft:damage_taken":21,"minecraft:walk_one_cm":18793,"minecraft:sneak_time":24,"minecraft:jump":41,"minecraft:damage_dealt":10,"minecraft:leave_game":1,"minecraft:time_since_death":9593,"minecraft:total_world_time":9649,"minecraft:interact_with_crafting_table":1,"minecraft:fall_one_cm":335,"minecraft:fly_one_cm":3252},"minecraft:picked_up":{"minecraft:raw_copper":2,"minecraft:torch":2,"minecraft:diorite":27,"minecraft:coal":20,"minecraft:cobblestone":16},"minecraft:mined":{"minecraft:coal_ore":20,"utdmod:ritual_block":1,"minecraft:copper_ore":1,"minecraft:cobblestone":1,"minecraft:stone":15,"minecraft:diorite":27,"minecraft:wall_torch":2}},"DataVersion":3700}